slangpy/__init__.py
slangpy/slangpy.py
slangpy/bin/libslang.so
slangpy/bin/slang.dll
slangpy/bin/slangc
slangpy/bin/slangc.exe
slangpy/util/__init__.py
slangpy/util/builtin_wrappers.py
slangpy/util/compile.py
slangpy/util/wrapper.py
slangpy-1.2.0.dist-info/METADATA
slangpy-1.2.0.dist-info/WHEEL
slangpy-1.2.0.dist-info/licenses/LICENSE
slangpy-1.2.0.dist-info/RECORD
