Metadata-Version: 2.1
Name: slangpy
Version: 1.2.0
Summary: A package for calling Slang modules from Python and PyTorch.
Project-URL: Homepage, https://github.com/shader-slang/slang
Project-URL: Bug Tracker, https://github.com/shader-slang/slang-python/issues
Author: Slang Development Team
License-File: LICENSE
Classifier: License :: OSI Approved :: MIT License
Classifier: Operating System :: OS Independent
Classifier: Programming Language :: Python :: 3
Requires-Python: >=3.7
Requires-Dist: filelock
Requires-Dist: hatchling>=1.11.0
Requires-Dist: ninja
Requires-Dist: torch>=1.1.0
